hana_ai/__init__.py
hana_ai/smart_dataframe.py
hana_ai/utility.py
hana_ai/agents/__init__.py
hana_ai/agents/hana_dataframe_agent.py
hana_ai/agents/hana_dataframe_prompt.py
hana_ai/agents/hana_sql_agent.py
hana_ai/agents/hanaml_agent_with_memory.py
hana_ai/agents/hanaml_rag_agent.py
hana_ai/agents/utilities.py
hana_ai/agents/hana_agent/__init__.py
hana_ai/agents/hana_agent/agent_base.py
hana_ai/agents/hana_agent/data_agent.py
hana_ai/agents/hana_agent/discovery_agent.py
hana_ai/agents/hana_agent/progress_monitor.py
hana_ai/agents/hana_agent/utility.py
hana_ai/client/mcp_client.py
hana_ai/tools/__init__.py
hana_ai/tools/agent_as_a_tool.py
hana_ai/tools/code_template_tools.py
hana_ai/tools/mcp_tools.py
hana_ai/tools/toolkit.py
hana_ai/tools/df_tools/__init__.py
hana_ai/tools/df_tools/additive_model_forecast_tools.py
hana_ai/tools/df_tools/automatic_timeseries_tools.py
hana_ai/tools/df_tools/fetch_tools.py
hana_ai/tools/df_tools/intermittent_forecast_tools.py
hana_ai/tools/df_tools/ts_outlier_detection_tools.py
hana_ai/tools/df_tools/ts_visualizer_tools.py
hana_ai/tools/hana_ml_tools/__init__.py
hana_ai/tools/hana_ml_tools/additive_model_forecast_tools.py
hana_ai/tools/hana_ml_tools/automatic_timeseries_tools.py
hana_ai/tools/hana_ml_tools/cap_artifacts_tools.py
hana_ai/tools/hana_ml_tools/fetch_tools.py
hana_ai/tools/hana_ml_tools/graph_tools.py
hana_ai/tools/hana_ml_tools/hdi_artifacts_tools.py
hana_ai/tools/hana_ml_tools/intermittent_forecast_tools.py
hana_ai/tools/hana_ml_tools/massive_automatic_timeseries_tools.py
hana_ai/tools/hana_ml_tools/massive_ts_outlier_detection_tools.py
hana_ai/tools/hana_ml_tools/model_storage_tools.py
hana_ai/tools/hana_ml_tools/select_statement_to_table_tools.py
hana_ai/tools/hana_ml_tools/ts_accuracy_measure_tools.py
hana_ai/tools/hana_ml_tools/ts_check_tools.py
hana_ai/tools/hana_ml_tools/ts_make_predict_table.py
hana_ai/tools/hana_ml_tools/ts_outlier_detection_tools.py
hana_ai/tools/hana_ml_tools/ts_visualizer_tools.py
hana_ai-1.0.25122300.dist-info/licenses/LICENSE
hana_ai-1.0.25122300.dist-info/METADATA
hana_ai-1.0.25122300.dist-info/WHEEL
hana_ai-1.0.25122300.dist-info/top_level.txt
hana_ai-1.0.25122300.dist-info/RECORD
