Metadata-Version: 2.4
Name: hana_ai
Version: 1.0.25122300
Summary: Generative AI Toolkit for SAP HANA Cloud
Author: SAP
License: Apache-2.0
Project-URL: Homepage, https://github.com/SAP/generative-ai-toolkit-for-sap-hana-cloud
Project-URL: Documentation, https://sap.github.io/generative-ai-toolkit-for-sap-hana-cloud/
Project-URL: Report Issues, https://github.com/SAP/generative-ai-toolkit-for-sap-hana-cloud/issues
Project-URL: Notebook Examples, https://github.com/SAP/generative-ai-toolkit-for-sap-hana-cloud/tree/main/nutest/testscripts
Keywords: Generative AI Toolkit SAP HANA Cloud
Requires-Python: >=3.0
License-File: LICENSE
Requires-Dist: langchain-community==0.3.27
Requires-Dist: langchain-experimental==0.3.3
Requires-Dist: langchain-text-splitters==0.3.9
Requires-Dist: numpy
Requires-Dist: pandas
Requires-Dist: hana-ml>=2.27.25122200
Requires-Dist: pydantic<2.13,>=2.11
Requires-Dist: sap-ai-sdk-gen[all]==5.10.0
Requires-Dist: fastmcp>=2.0
Dynamic: license-file
